tf_lambda/__init__.py
tf_lambda/lambda_layer.py
tf_lambda/layers/__init__.py
tf_lambda/layers/lambda_conv.py
tf_lambda/layers/lambda_layer.py
tf_lambda-0.4.0.dist-info/LICENSE
tf_lambda-0.4.0.dist-info/METADATA
tf_lambda-0.4.0.dist-info/WHEEL
tf_lambda-0.4.0.dist-info/top_level.txt
tf_lambda-0.4.0.dist-info/RECORD
