Metadata-Version: 2.1
Name: tf-lambda
Version: 0.4.0
Summary: A TensorFlow 2 implementation of LambdaNetworks.
Home-page: https://github.com/seanmor5/tf_lambda
Author: Sean Moriarity
Author-email: smoriarity.5@gmail.com
License: UNKNOWN
Platform: UNKNOWN
Classifier: Programming Language :: Python :: 3
Classifier: License :: OSI Approved :: MIT License
Classifier: Operating System :: OS Independent
Requires-Python: >=3.6
Requires-Dist: einops
